opentemplate-0.4.3.dist-info/METADATA
opentemplate-0.4.3.dist-info/WHEEL
opentemplate-0.4.3.dist-info/entry_points.txt
opentemplate/__init__.py
opentemplate/py.typed
opentemplate/py.typed.license
opentemplate-0.4.3.dist-info/RECORD
