Metadata-Version: 2.4
Name: opentemplate
Version: 0.4.3
Summary: All-in-one Python template. One click. Everything included.
Author: open-nudge
Maintainer: open-nudge
License-Expression: Apache-2.0
Classifier: Development Status :: 2 - Pre-Alpha
Classifier: Intended Audience :: Developers
Classifier: Programming Language :: Python
Classifier: Programming Language :: Python :: 3 :: Only
Classifier: Programming Language :: Python :: 3.11
Classifier: Programming Language :: Python :: 3.12
Classifier: Programming Language :: Python :: 3.13
Classifier: Topic :: Software Development :: Libraries
Classifier: Topic :: Software Development :: Libraries :: Python Modules
Classifier: Typing :: Typed
Project-URL: Changelog, https://github.com/open-nudge/opentemplate/blob/master/CHANGELOG.md
Project-URL: Documentation, https://open-nudge.github.io/opentemplate
Project-URL: Homepage, https://open-nudge.github.io/opentemplate
Project-URL: Issues, https://github.com/open-nudge/opentemplate/issues
Project-URL: Repository, https://github.com/open-nudge/opentemplate
Requires-Python: >=3.11
